plotx/__init__.py
plotx/plotx.py
plotx-0.0.9.dist-info/LICENSE
plotx-0.0.9.dist-info/METADATA
plotx-0.0.9.dist-info/WHEEL
plotx-0.0.9.dist-info/top_level.txt
plotx-0.0.9.dist-info/RECORD
